nonebot_plugin_clock/__init__.py
nonebot_plugin_clock/clock.py
nonebot_plugin_clock/config.py
nonebot_plugin_clock/database/database.py
nonebot_plugin_clock/handle.py
nonebot_plugin_clock/model/__init__.py
nonebot_plugin_clock/model/Clock.py
nonebot_plugin_clock/natural_language_clock.py
nonebot_plugin_clock/README.md
nonebot_plugin_clock/scheduler.py
nonebot_plugin_clock/tools/_Holiday_info.py
nonebot_plugin_clock/utils.py
nonebot_plugin_clock-1.1.6.dist-info/licenses/LICENSE
nonebot_plugin_clock-1.1.6.dist-info/METADATA
nonebot_plugin_clock-1.1.6.dist-info/WHEEL
nonebot_plugin_clock-1.1.6.dist-info/RECORD
