Metadata-Version: 2.4
Name: nonebot-plugin-clock
Version: 1.1.6
Summary: Nonebot2 plugin for using llm
License: MIT
License-File: LICENSE
Author: Zeta-qixi
Author-email: 1019289695@qq.com
Requires-Python: >=3.10,<4.0
Classifier: License :: OSI Approved :: MIT License
Classifier: Programming Language :: Python :: 3
Classifier: Programming Language :: Python :: 3.10
Classifier: Programming Language :: Python :: 3.11
Classifier: Programming Language :: Python :: 3.12
Classifier: Programming Language :: Python :: 3.13
Classifier: Programming Language :: Python :: 3.14
Requires-Dist: nonebot-adapter-onebot (>=2.4.3,<3.0.0)
Requires-Dist: nonebot-adapter-qq
Requires-Dist: nonebot-plugin-apscheduler
Requires-Dist: nonebot-plugin-localstore
Requires-Dist: nonebot2 (>=2.4.1,<3.0.0)
Requires-Dist: requests
Project-URL: Homepage, https://github.com/Zeta-qixi/nonebot-plugin-clock
